LICENSE
MANIFEST.in
README.md
setup.cfg
setup.py
pyshould/__init__.py
pyshould/__main__.py
pyshould/dsl.py
pyshould/dumper.py
pyshould/expect.py
pyshould/expectation.py
pyshould/matchers.py
pyshould/patch.py
pyshould/patch_mockito.py
pyshould/patched.py
pyshould.egg-info/PKG-INFO
pyshould.egg-info/SOURCES.txt
pyshould.egg-info/dependency_links.txt
pyshould.egg-info/not-zip-safe
pyshould.egg-info/requires.txt
pyshould.egg-info/top_level.txt
tests/__init__.py
tests/coordination.py
tests/dsl.py
tests/expect.py
tests/patch.py