Metadata-Version: 1.0
Name: pyshould
Version: 0.7.1
Summary: Should style asserts based on pyhamcrest
Home-page: https://github.com/drslump/pyshould
Author: Ivan -DrSlump- Montes
Author-email: drslump@pollinimini.net
License: MIT
Platform: UNKNOWN
